Lazy_cleaner/Lazy_cleaner.py
Lazy_cleaner/__init__.py
Lazy_cleaner-0.0.9.dist-info/LICENSE
Lazy_cleaner-0.0.9.dist-info/METADATA
Lazy_cleaner-0.0.9.dist-info/WHEEL
Lazy_cleaner-0.0.9.dist-info/top_level.txt
Lazy_cleaner-0.0.9.dist-info/RECORD
